eegain/__init__.py
eegain/version.py
eegain/data/__init__.py
eegain/data/datasets.py
eegain/data/loader.py
eegain/models/__init__.py
eegain/models/_registry.py
eegain/models/conformer.py
eegain/models/deepconvnet.py
eegain/models/eegnet.py
eegain/models/shallowconvnet.py
eegain/models/tsception.py
eegain/transforms/__init__.py
eegain/transforms/transforms.py
eegain-0.0.3.dist-info/METADATA
eegain-0.0.3.dist-info/WHEEL
eegain-0.0.3.dist-info/top_level.txt
eegain-0.0.3.dist-info/RECORD
