Metadata-Version: 2.1
Name: eegain
Version: 0.0.3
Summary: EEG emotion recognition package for standardization
Home-page: https://github.com/RRaphaell/EEGain
Author: GAIN Team
Author-email: 
Keywords: EEG,emotion recognition,framework,package,standardized
Classifier: Intended Audience :: Education
Classifier: Intended Audience :: Science/Research
Classifier: Programming Language :: Python :: 3.7
Classifier: Programming Language :: Python :: 3.8
Classifier: Programming Language :: Python :: 3.9
Classifier: Programming Language :: Python :: 3.10
Classifier: Programming Language :: Python :: 3.11
Classifier: Topic :: Scientific/Engineering
Classifier: Topic :: Scientific/Engineering :: Artificial Intelligence
Classifier: Topic :: Scientific/Engineering :: Human Machine Interfaces
Requires-Python: >=3.7
Requires-Dist: torch
Requires-Dist: mne
Requires-Dist: numpy
Requires-Dist: sklearn
Requires-Dist: tqdm
